yslee_sense_api/__init__.py
yslee_sense_api/api_client.py
yslee_sense_api/configuration.py
yslee_sense_api/exceptions.py
yslee_sense_api/model_utils.py
yslee_sense_api/rest.py
yslee_sense_api/api/__init__.py
yslee_sense_api/api/audio_session_api.py
yslee_sense_api/apis/__init__.py
yslee_sense_api/model/__init__.py
yslee_sense_api/model/audio_chunk.py
yslee_sense_api/model/create_session.py
yslee_sense_api/model/created_session.py
yslee_sense_api/model/default_sensitivity.py
yslee_sense_api/model/generic_error.py
yslee_sense_api/model/page.py
yslee_sense_api/model/predict_request.py
yslee_sense_api/model/predict_response.py
yslee_sense_api/model/sense.py
yslee_sense_api/model/sense_event.py
yslee_sense_api/model/sense_event_tag.py
yslee_sense_api/model/session_refs.py
yslee_sense_api/model/session_result.py
yslee_sense_api/model/session_status.py
yslee_sense_api/model/session_type.py
yslee_sense_api/model/tags_sensitivity.py
yslee_sense_api/model/update_session.py
yslee_sense_api/models/__init__.py
yslee_sense_api-1.7.90.dist-info/METADATA
yslee_sense_api-1.7.90.dist-info/WHEEL
yslee_sense_api-1.7.90.dist-info/RECORD
