Metadata-Version: 2.3
Name: yslee-sense-api
Version: 1.7.90
Summary: Yslee Sense API
Project-URL: Homepage, https://github.com/ysleeearai/sense-api-samples
Project-URL: Issues, https://github.com/ysleeearai/sense-api-samples/issues
Author-email: Yslee <support@yslee.ai>
Classifier: License :: OSI Approved :: MIT License
Classifier: Operating System :: OS Independent
Classifier: Programming Language :: Python :: 3
Requires-Python: >=3.8
Requires-Dist: python-dateutil>=2.9.0
Requires-Dist: setuptools>=21.0.0
Requires-Dist: urllib3>=2.2.3
